[
  {
    "label": "First name",
    "value": "Jay"
  },
  {
    "label": "Last name",
    "value": "Kumar Gupta"
  },
  {
    "label": "Full name",
    "value": "Jay Kumar Gupta"
  },
  {
    "label": "Email",
    "value": "aarav@example.com"
  },
  {
    "label": "Confirm your email",
    "value": "aarav@example.com"
  },
  {
    "label": "City",
    "value": "Bengaluru"
  },
  {
    "label": "Phone number",
    "value": "+91-7320967983"
  },
  {
    "label": "Degree",
    "value": "B.Tech in Computer ScienceCGPA: 8.67"
  },
  {
    "label": "Graduation year",
    "value": "2020"
  },
  {
    "label": "Preferred location",
    "value": "Bengaluru"
  },
  {
    "label": "Target role",
    "value": "Software Engineer"
  },
  {
    "label": "Work authorization",
    "value": "Yes"
  },
  {
    "label": "Legally authorized to work",
    "value": "Yes"
  },
  {
    "label": "Visa sponsorship required",
    "value": "No"
  },
  {
    "label": "Visa required",
    "value": "No"
  },
  {
    "label": "Current CTC",
    "value": "0 LPA"
  },
  {
    "label": "Current salary",
    "value": "0 LPA"
  },
  {
    "label": "Expected salary",
    "value": "10 LPA"
  },
  {
    "label": "Expected CTC",
    "value": "10 LPA"
  },
  {
    "label": "Message to the Hiring Team",
    "value": "I am excited to apply for the Software Engineer, AI Solutions(Contarct-12 Months) role at Jobs, where I can bring my JavaScript, React, Next.js experience as an aspiring Software Engineer."
  },
  {
    "label": "Primary skills",
    "value": "JavaScript, React, Next.js, Node.js, Express"
  },
  {
    "label": "Resume context",
    "value": "jay_kumar_gupta_nit_kkr.pdf"
  },
  {
    "label": "Why are you interested in this role?",
    "value": "This role aligns with my goal of becoming a Software Engineer and uses skills I have practiced through projects and coursework."
  },
  {
    "label": "What makes you a match?",
    "value": "My background in JavaScript, React, Next.js, Node.js closely matches the expectations in this job description."
  }
]
